[
    {
        "id": 1,
        "nombre": "Imagine",
        "duracion": "3:04",
        "artista": "John Lennon",
        "album": "Imagine",
        "anio": 1971,
        "genero": "Rock"
    },
    {
        "id": 2,
        "nombre": "Bohemian Rhapsody",
        "duracion": "5:55",
        "artista": "Queen",
        "album": "A Night at the Opera",
        "anio": 1975,
        "genero": "Rock"
    },
    {
        "id": 3,
        "nombre": "Shape of You",
        "duracion": "3:53",
        "artista": "Ed Sheeran",
        "album": "Divide",
        "anio": 2017,
        "genero": "Pop"
    }
]